{"id_hochschule":313,"id_studien":226,"name":"Ostbayerische Technische Hochschule Regensburg","steckbrief":{"Hochschule":"Ostbayerische Technische Hochschule Regensburg","Hochschulleitung":"Herr Prof. Dr. Wolfgang Baier","":"","Hochschultyp":"Fachhochschulen / HAW","Bundesland":"Bayern","Trägerschaft":"öffentlich-rechtlich","Promotionsrecht":"Nein","Habilitationsrecht":"Nein","Gründungsjahr":"1971","Studierendenzahl":"10809 (WS 2016/2017)","Nationaler Kodex":"Ja"},"anschrift":{"Hausanschrift":"Prüfeninger Straße 58, 93049 Regensburg","Telefon":"0941 943-02","Postanschrift":"Postfach 12 03 27, 93025 Regensburg","E-Mail":"poststelle(at)oth-regensburg.de"}}