{"id_hochschule":337,"id_studien":156,"name":"AKAD Hochschule Stuttgart - staatlich anerkannt","steckbrief":{"Hochschule":"AKAD Hochschule Stuttgart - staatlich anerkannt","Hochschulleitung":"Herr Prof. Dr. Torsten B체gner","":"","Hochschultyp":"Fachhochschulen / HAW","Bundesland":"Baden-W체rttemberg","Tr채gerschaft":"privat, staatlich anerkannt","Promotionsrecht":"Nein","Habilitationsrecht":"Nein","Gr체ndungsjahr":"1991","Studierendenzahl":"4855 (WS 2016/2017)"},"anschrift":{"Hausanschrift":"Heilbronner Str. 86, 70191 Stuttgart","E-Mail":"beratung(at)akad.de","Telefon":"0711 81495-400"}}