[{"id_hochschule":5,"id_studien":312,"name":"Angewandte  Ingenieurwissenschaften","id_studiengang":312,"Hochschule":"Hochschule Ansbach","Studienort":"Ansbach","Abschluss":"Bachelor of Engineering","Studientyp":"grundständig","Studienform":"Vollzeitstudium"},{"id_hochschule":5,"id_studien":312,"name":"Angewandte Kunststofftechnik","id_studiengang":1,"Hochschule":"Hochschule Ansbach","Studienort":"Ansbach","Abschluss":"Bachelor of Engineering","Studientyp":"grundständig","Studienform":"Berufsbegleitend, Teilzeitstudium"},{"id_hochschule":5,"id_studien":312,"name":"Betriebswirtschaft","id_studiengang":2,"Hochschule":"Hochschule Ansbach","Studienort":"Ansbach","Abschluss":"Bachelor of Arts","Studientyp":"grundständig","Studienform":"Vollzeitstudium"},{"id_hochschule":5,"id_studien":312,"name":"Biomedizinische Technik","id_studiengang":3,"Hochschule":"Hochschule Ansbach","Studienort":"Ansbach","Abschluss":"Bachelor of Engineering","Studientyp":"grundständig","Studienform":"Vollzeitstudium"},{"id_hochschule":5,"id_studien":312,"name":"Energiemanagement und Energietechnik","id_studiengang":4,"Hochschule":"Hochschule Ansbach,Hochschule Weihenstephan-Triesdorf,Technische Hochschule Nürnberg","Studienort":"Ansbach, Freising, Nürnberg","Abschluss":"Master of Engineering","Studientyp":"weiterführend","Studienform":"Vollzeitstudium"},{"id_hochschule":5,"id_studien":312,"name":"Industrielle Biotechnologie","id_studiengang":5,"Hochschule":"Hochschule Ansbach","Studienort":"Ansbach","Abschluss":"Bachelor of Science","Studientyp":"grundständig","Studienform":"Vollzeitstudium"},{"id_hochschule":5,"id_studien":312,"name":"Interkulturelles Management","id_studiengang":6,"Hochschule":"Hochschule Ansbach","Studienort":"Ansbach","Abschluss":"Bachelor of Arts","Studientyp":"grundständig","Studienform":"Vollzeitstudium"},{"id_hochschule":5,"id_studien":312,"name":"Interkulturelles Management (Teilzeit)","id_studiengang":7,"Hochschule":"Hochschule Ansbach","Studienort":"Ansbach","Abschluss":"Bachelor of Arts","Studientyp":"grundständig","Studienform":"Teilzeitstudium"},{"id_hochschule":5,"id_studien":312,"name":"Internationales Produkt- und Servicemanagement","id_studiengang":8,"Hochschule":"Hochschule Ansbach","Studienort":"Ansbach","Abschluss":"Master of Arts","Studientyp":"weiterführend","Studienform":"Internationaler Studiengang, Vollzeitstudium"},{"id_hochschule":5,"id_studien":312,"name":"Kreatives Management","id_studiengang":9,"Hochschule":"Hochschule Ansbach","Studienort":"Ansbach","Abschluss":"MBA Master of Business Administration","Studientyp":"weiterführend","Studienform":"Berufsbegleitend"},{"id_hochschule":5,"id_studien":312,"name":"Medizintechnik","id_studiengang":10,"Hochschule":"Hochschule Ansbach","Studienort":"Ansbach","Abschluss":"Master of Engineering","Studientyp":"weiterführend","Studienform":"Vollzeitstudium"},{"id_hochschule":5,"id_studien":312,"name":"Multimediale Information und Kommunikation","id_studiengang":11,"Hochschule":"Hochschule Ansbach","Studienort":"Ansbach","Abschluss":"Master of Arts","Studientyp":"weiterführend","Studienform":"Vollzeitstudium"},{"id_hochschule":5,"id_studien":312,"name":"Multimedia und Kommunikation","id_studiengang":12,"Hochschule":"Hochschule Ansbach","Studienort":"Ansbach","Abschluss":"Bachelor of Arts","Studientyp":"grundständig","Studienform":"Vollzeitstudium"},{"id_hochschule":5,"id_studien":312,"name":"Ressortjournalismus","id_studiengang":13,"Hochschule":"Hochschule Ansbach","Studienort":"Ansbach","Abschluss":"Bachelor of Arts","Studientyp":"grundständig","Studienform":"Vollzeitstudium"},{"id_hochschule":5,"id_studien":312,"name":"Strategisches Management","id_studiengang":14,"Hochschule":"Hochschule Ansbach","Studienort":"Ansbach","Abschluss":"Bachelor of Arts","Studientyp":"grundständig","Studienform":"Berufsbegleitend, Teilzeitstudium"},{"id_hochschule":5,"id_studien":312,"name":"Wertschöpfungsmanagement","id_studiengang":15,"Hochschule":"Hochschule Ansbach","Studienort":"Ansbach","Abschluss":"Bachelor of Arts","Studientyp":"grundständig","Studienform":"Berufsbegleitend, Teilzeitstudium"},{"id_hochschule":5,"id_studien":312,"name":"Wirtschaftsinformatik","id_studiengang":16,"Hochschule":"Hochschule Ansbach","Studienort":"Ansbach","Abschluss":"Bachelor of Arts","Studientyp":"grundständig","Studienform":"Vollzeitstudium"},{"id_hochschule":5,"id_studien":312,"name":"Wirtschaftsingenieurwesen","id_studiengang":17,"Hochschule":"Hochschule Ansbach","Studienort":"Ansbach","Abschluss":"Bachelor of Engineering","Studientyp":"grundständig","Studienform":"Vollzeitstudium"}]