[{"id_hochschule":274,"id_studien":366,"name":"Animation","id_studiengang":366,"Hochschule":"Hochschule Macromedia","Studienort":"München","Abschluss":"Bachelor of Arts","Studientyp":"grundständig","Studienform":"Vollzeitstudium"},{"id_hochschule":274,"id_studien":366,"name":"Brand Management","id_studiengang":1,"Hochschule":"Hochschule Macromedia","Studienort":"Hamburg, Köln, u.a.","Abschluss":"Master of Arts","Studientyp":"weiterführend","Studienform":"Vollzeitstudium"},{"id_hochschule":274,"id_studien":366,"name":"Brand Management (Englisch)","id_studiengang":2,"Hochschule":"Hochschule Macromedia","Studienort":"Berlin , München","Abschluss":"Master of Arts","Studientyp":"weiterführend","Studienform":"Internationaler Studiengang, Vollzeitstudium"},{"id_hochschule":274,"id_studien":366,"name":"Business","id_studiengang":3,"Hochschule":"Hochschule Macromedia","Studienort":"München","Abschluss":"Master of Arts","Studientyp":"weiterführend","Studienform":"Internationaler Studiengang, Vollzeitstudium"},{"id_hochschule":274,"id_studien":366,"name":"Business Management","id_studiengang":4,"Hochschule":"Hochschule Macromedia","Studienort":"Hamburg, Köln, u.a.","Abschluss":"Master of Arts","Studientyp":"weiterführend","Studienform":"Vollzeitstudium"},{"id_hochschule":274,"id_studien":366,"name":"Design","id_studiengang":5,"Hochschule":"Hochschule Macromedia","Studienort":"Berlin, Hamburg, u.a.","Abschluss":"Bachelor of Arts","Studientyp":"grundständig","Studienform":"Vollzeitstudium"},{"id_hochschule":274,"id_studien":366,"name":"Design Management","id_studiengang":6,"Hochschule":"Hochschule Macromedia","Studienort":"Berlin","Abschluss":"Master of Arts","Studientyp":"weiterführend","Studienform":"Vollzeitstudium"},{"id_hochschule":274,"id_studien":366,"name":"Design Management","id_studiengang":7,"Hochschule":"Hochschule Macromedia","Studienort":"München","Abschluss":"Master of Arts","Studientyp":"weiterführend","Studienform":"Internationaler Studiengang, Vollzeitstudium"},{"id_hochschule":274,"id_studien":366,"name":"Design Thinking (Englisch)","id_studiengang":8,"Hochschule":"Hochschule Macromedia","Studienort":"München","Abschluss":"Master of Arts","Studientyp":"weiterführend","Studienform":"Internationaler Studiengang, Vollzeitstudium"},{"id_hochschule":274,"id_studien":366,"name":"Digital Experience Design","id_studiengang":9,"Hochschule":"Hochschule Macromedia","Studienort":"München","Abschluss":"Bachelor of Arts","Studientyp":"grundständig","Studienform":"Vollzeitstudium"},{"id_hochschule":274,"id_studien":366,"name":"Digital Media Business","id_studiengang":10,"Hochschule":"Hochschule Macromedia","Studienort":"Berlin , München","Abschluss":"Master of Arts","Studientyp":"weiterführend","Studienform":"Vollzeitstudium"},{"id_hochschule":274,"id_studien":366,"name":"Drehbuch","id_studiengang":11,"Hochschule":"Hochschule Macromedia","Studienort":"Köln , München","Abschluss":"Bachelor of Arts","Studientyp":"grundständig","Studienform":"Vollzeitstudium"},{"id_hochschule":274,"id_studien":366,"name":"Entertainmentmanagement","id_studiengang":12,"Hochschule":"Hochschule Macromedia","Studienort":"Köln , Stuttgart","Abschluss":"Bachelor of Arts","Studientyp":"grundständig","Studienform":"Vollzeitstudium"},{"id_hochschule":274,"id_studien":366,"name":"Eventmanagement","id_studiengang":13,"Hochschule":"Hochschule Macromedia","Studienort":"Hamburg, Köln, u.a.","Abschluss":"Bachelor of Arts","Studientyp":"grundständig","Studienform":"Vollzeitstudium"},{"id_hochschule":274,"id_studien":366,"name":"Fashion Journalismus","id_studiengang":14,"Hochschule":"Hochschule Macromedia","Studienort":"Köln, München, u.a.","Abschluss":"Bachelor of Arts","Studientyp":"grundständig","Studienform":"Vollzeitstudium"},{"id_hochschule":274,"id_studien":366,"name":"Fashion Management","id_studiengang":15,"Hochschule":"Hochschule Macromedia","Studienort":"Berlin, Hamburg, u.a.","Abschluss":"Bachelor of Arts","Studientyp":"grundständig","Studienform":"Internationaler Studiengang, Vollzeitstudium"},{"id_hochschule":274,"id_studien":366,"name":"Film und Fernsehen","id_studiengang":16,"Hochschule":"Hochschule Macromedia","Studienort":"Köln , München","Abschluss":"Bachelor of Arts","Studientyp":"grundständig","Studienform":"Vollzeitstudium"},{"id_hochschule":274,"id_studien":366,"name":"Finanzmanagement und Controlling","id_studiengang":17,"Hochschule":"Hochschule Macromedia","Studienort":"Hamburg, München, u.a.","Abschluss":"Bachelor of Arts","Studientyp":"grundständig","Studienform":"Vollzeitstudium"},{"id_hochschule":274,"id_studien":366,"name":"Game Design","id_studiengang":18,"Hochschule":"Hochschule Macromedia","Studienort":"Stuttgart","Abschluss":"Bachelor of Arts","Studientyp":"grundständig","Studienform":"Vollzeitstudium"},{"id_hochschule":274,"id_studien":366,"name":"Internationales Management","id_studiengang":19,"Hochschule":"Hochschule Macromedia","Studienort":"Hamburg, Köln, u.a.","Abschluss":"Bachelor of Arts","Studientyp":"grundständig","Studienform":"Vollzeitstudium"},{"id_hochschule":274,"id_studien":366,"name":"International Management","id_studiengang":20,"Hochschule":"Hochschule Macromedia","Studienort":"Berlin , München","Abschluss":"Bachelor of Arts","Studientyp":"grundständig","Studienform":"Internationaler Studiengang, Vollzeitstudium"},{"id_hochschule":274,"id_studien":366,"name":"Journalismus","id_studiengang":21,"Hochschule":"Hochschule Macromedia","Studienort":"Berlin, Hamburg, u.a.","Abschluss":"Bachelor of Arts","Studientyp":"grundständig","Studienform":"Vollzeitstudium"},{"id_hochschule":274,"id_studien":366,"name":"Journalistik","id_studiengang":22,"Hochschule":"Hochschule Macromedia","Studienort":"Hamburg, Köln, u.a.","Abschluss":"Bachelor of Arts","Studientyp":"grundständig","Studienform":"Vollzeitstudium"},{"id_hochschule":274,"id_studien":366,"name":"Kamera","id_studiengang":23,"Hochschule":"Hochschule Macromedia","Studienort":"Köln , München","Abschluss":"Bachelor of Arts","Studientyp":"grundständig","Studienform":"Vollzeitstudium"},{"id_hochschule":274,"id_studien":366,"name":"Luxury und Fashion Management","id_studiengang":24,"Hochschule":"Hochschule Macromedia","Studienort":"Köln, München, u.a.","Abschluss":"Master of Arts","Studientyp":"weiterführend","Studienform":"Vollzeitstudium"},{"id_hochschule":274,"id_studien":366,"name":"Management","id_studiengang":25,"Hochschule":"Hochschule Macromedia","Studienort":"Berlin, Hamburg, u.a.","Abschluss":"Bachelor of Arts","Studientyp":"grundständig","Studienform":"Vollzeitstudium"},{"id_hochschule":274,"id_studien":366,"name":"Markenkommunikation und Werbung","id_studiengang":26,"Hochschule":"Hochschule Macromedia","Studienort":"Berlin, Hamburg, u.a.","Abschluss":"Bachelor of Arts","Studientyp":"grundständig","Studienform":"Vollzeitstudium"},{"id_hochschule":274,"id_studien":366,"name":"Marketingmanagement","id_studiengang":27,"Hochschule":"Hochschule Macromedia","Studienort":"Hamburg, Köln, u.a.","Abschluss":"Bachelor of Arts","Studientyp":"grundständig","Studienform":"Vollzeitstudium"},{"id_hochschule":274,"id_studien":366,"name":"Media and Communication Design","id_studiengang":28,"Hochschule":"Hochschule Macromedia","Studienort":"Berlin","Abschluss":"Bachelor of Arts","Studientyp":"grundständig","Studienform":"Internationaler Studiengang, Vollzeitstudium"},{"id_hochschule":274,"id_studien":366,"name":"Media and Communication Management","id_studiengang":29,"Hochschule":"Hochschule Macromedia","Studienort":"Berlin, Hamburg, u.a.","Abschluss":"Bachelor of Arts","Studientyp":"grundständig","Studienform":"Internationaler Studiengang, Vollzeitstudium"},{"id_hochschule":274,"id_studien":366,"name":"Media and Communication Management","id_studiengang":30,"Hochschule":"Hochschule Macromedia","Studienort":"Berlin , München","Abschluss":"Master of Arts","Studientyp":"weiterführend","Studienform":"Internationaler Studiengang, Vollzeitstudium"},{"id_hochschule":274,"id_studien":366,"name":"Medienmanagement","id_studiengang":31,"Hochschule":"Hochschule Macromedia","Studienort":"Berlin, Hamburg, u.a.","Abschluss":"Bachelor of Arts","Studientyp":"grundständig","Studienform":"Vollzeitstudium"},{"id_hochschule":274,"id_studien":366,"name":"Medien- und Kommunikationsdesign","id_studiengang":32,"Hochschule":"Hochschule Macromedia","Studienort":"Berlin, Hamburg, u.a.","Abschluss":"Bachelor of Arts","Studientyp":"grundständig","Studienform":"Vollzeitstudium"},{"id_hochschule":274,"id_studien":366,"name":"Medien- und Kommunikationsmanagement","id_studiengang":33,"Hochschule":"Hochschule Macromedia","Studienort":"Berlin, Hamburg, u.a.","Abschluss":"Bachelor of Arts","Studientyp":"grundständig","Studienform":"Vollzeitstudium"},{"id_hochschule":274,"id_studien":366,"name":"Medien- und Kommunikationsmanagement","id_studiengang":34,"Hochschule":"Hochschule Macromedia","Studienort":"Hamburg, Köln, u.a.","Abschluss":"Master of Arts","Studientyp":"weiterführend","Studienform":"Vollzeitstudium"},{"id_hochschule":274,"id_studien":366,"name":"Medien- und Werbepsychologie","id_studiengang":35,"Hochschule":"Hochschule Macromedia","Studienort":"Berlin, Hamburg, u.a.","Abschluss":"Bachelor of Arts","Studientyp":"grundständig","Studienform":"Vollzeitstudium"},{"id_hochschule":274,"id_studien":366,"name":"Musikmanagement","id_studiengang":36,"Hochschule":"Hochschule Macromedia","Studienort":"Berlin, Hamburg, u.a.","Abschluss":"Bachelor of Arts","Studientyp":"grundständig","Studienform":"Vollzeitstudium"},{"id_hochschule":274,"id_studien":366,"name":"Postproduktion","id_studiengang":37,"Hochschule":"Hochschule Macromedia","Studienort":"Köln , München","Abschluss":"Bachelor of Arts","Studientyp":"grundständig","Studienform":"Vollzeitstudium"},{"id_hochschule":274,"id_studien":366,"name":"PR und Corporate Communication","id_studiengang":38,"Hochschule":"Hochschule Macromedia","Studienort":"Hamburg, Köln, u.a.","Abschluss":"Bachelor of Arts","Studientyp":"grundständig","Studienform":"Vollzeitstudium"},{"id_hochschule":274,"id_studien":366,"name":"Regie","id_studiengang":39,"Hochschule":"Hochschule Macromedia","Studienort":"Köln , München","Abschluss":"Bachelor of Arts","Studientyp":"grundständig","Studienform":"Vollzeitstudium"},{"id_hochschule":274,"id_studien":366,"name":"Smart City Design","id_studiengang":40,"Hochschule":"Hochschule Macromedia","Studienort":"Berlin","Abschluss":"Master of Arts","Studientyp":"weiterführend","Studienform":"Internationaler Studiengang, Vollzeitstudium"},{"id_hochschule":274,"id_studien":366,"name":"Sportjournalismus","id_studiengang":41,"Hochschule":"Hochschule Macromedia","Studienort":"Hamburg, Köln, u.a.","Abschluss":"Bachelor of Arts","Studientyp":"grundständig","Studienform":"Vollzeitstudium"},{"id_hochschule":274,"id_studien":366,"name":"Sportmanagement","id_studiengang":42,"Hochschule":"Hochschule Macromedia","Studienort":"Hamburg, Köln, u.a.","Abschluss":"Bachelor of Arts","Studientyp":"grundständig","Studienform":"Vollzeitstudium"},{"id_hochschule":274,"id_studien":366,"name":"Sportmarketing","id_studiengang":43,"Hochschule":"Hochschule Macromedia","Studienort":"Hamburg, Köln, u.a.","Abschluss":"Master of Arts","Studientyp":"weiterführend","Studienform":"Vollzeitstudium"},{"id_hochschule":274,"id_studien":366,"name":"Sport- und Eventmanagement","id_studiengang":44,"Hochschule":"Hochschule Macromedia","Studienort":"Köln , Stuttgart","Abschluss":"Bachelor of Arts","Studientyp":"grundständig","Studienform":"Vollzeitstudium"},{"id_hochschule":274,"id_studien":366,"name":"Tourismusmanagement","id_studiengang":45,"Hochschule":"Hochschule Macromedia","Studienort":"Köln , München","Abschluss":"Bachelor of Arts","Studientyp":"grundständig","Studienform":"Vollzeitstudium"},{"id_hochschule":274,"id_studien":366,"name":"Unternehmenskommunikation","id_studiengang":46,"Hochschule":"Hochschule Macromedia","Studienort":"Hamburg , Köln","Abschluss":"Master of Arts","Studientyp":"weiterführend","Studienform":"Vollzeitstudium"},{"id_hochschule":274,"id_studien":366,"name":"Visual Effects","id_studiengang":47,"Hochschule":"Hochschule Macromedia","Studienort":"Köln , München","Abschluss":"Bachelor of Arts","Studientyp":"grundständig","Studienform":"Vollzeitstudium"},{"id_hochschule":274,"id_studien":366,"name":"Wirtschaftspsychologie","id_studiengang":48,"Hochschule":"Hochschule Macromedia","Studienort":"Hamburg, Köln, u.a.","Abschluss":"Bachelor of Arts","Studientyp":"grundständig","Studienform":"Vollzeitstudium"}]