[{"id_hochschule":338,"id_studien":398,"name":"Angewandte Gesundheits- und Pflegewissenschaften","id_studiengang":398,"Hochschule":"Duale Hochschule Baden-Württemberg","Studienort":"Heidenheim, Karlsruhe, u.a.","Abschluss":"Bachelor of Science","Studientyp":"grundständig","Studienform":"Ausbildungsintegrierend, Duales Studium, Praxisintegrierend, Vollzeitstudium"},{"id_hochschule":338,"id_studien":398,"name":"Angewandte Hebammenwissenschaft - Hebammenkunde","id_studiengang":1,"Hochschule":"Duale Hochschule Baden-Württemberg","Studienort":"Heidenheim , Karlsruhe","Abschluss":"Bachelor of Science","Studientyp":"grundständig","Studienform":"Ausbildungsintegrierend, Duales Studium, Praxisintegrierend, Vollzeitstudium"},{"id_hochschule":338,"id_studien":398,"name":"Angewandte Pflegewissenschaft","id_studiengang":2,"Hochschule":"Duale Hochschule Baden-Württemberg","Studienort":"Stuttgart","Abschluss":"Bachelor of Arts","Studientyp":"grundständig","Studienform":"Ausbildungsintegrierend, Duales Studium, Praxisintegrierend, Vollzeitstudium"},{"id_hochschule":338,"id_studien":398,"name":"Angewandte Pflegewissenschaften","id_studiengang":3,"Hochschule":"Duale Hochschule Baden-Württemberg","Studienort":"Stuttgart","Abschluss":"Bachelor of Arts","Studientyp":"grundständig","Studienform":"Berufsbegleitend, Duales Studium"},{"id_hochschule":338,"id_studien":398,"name":"Bauingenieurwesen - Fassadentechnik","id_studiengang":4,"Hochschule":"Duale Hochschule Baden-Württemberg","Studienort":"Mosbach","Abschluss":"Bachelor of Engineering","Studientyp":"grundständig","Studienform":"Duales Studium, Praxisintegrierend, Vollzeitstudium"},{"id_hochschule":338,"id_studien":398,"name":"Bauingenieurwesen - Öffentliches Bauen","id_studiengang":5,"Hochschule":"Duale Hochschule Baden-Württemberg","Studienort":"Mosbach","Abschluss":"Bachelor of Engineering","Studientyp":"grundständig","Studienform":"Duales Studium, Praxisintegrierend, Vollzeitstudium"},{"id_hochschule":338,"id_studien":398,"name":"Bauingenieurwesen - Projektmanagement","id_studiengang":6,"Hochschule":"Duale Hochschule Baden-Württemberg","Studienort":"Mosbach","Abschluss":"Bachelor of Engineering","Studientyp":"grundständig","Studienform":"Duales Studium, Praxisintegrierend, Vollzeitstudium"},{"id_hochschule":338,"id_studien":398,"name":"Biofasertechnik","id_studiengang":7,"Hochschule":"Duale Hochschule Baden-Württemberg","Studienort":"Bad Mergentheim, Friedrichshafen, u.a.","Abschluss":"Master of Engineering","Studientyp":"weiterführend","Studienform":"Berufsbegleitend, Berufsintegrierend, Duales Studium"},{"id_hochschule":338,"id_studien":398,"name":"Business Management - Accounting, Controlling und Steuern","id_studiengang":8,"Hochschule":"Duale Hochschule Baden-Württemberg","Studienort":"Bad Mergentheim, Friedrichshafen, u.a.","Abschluss":"Master of Arts","Studientyp":"weiterführend","Studienform":"Berufsbegleitend, Berufsintegrierend, Duales Studium"},{"id_hochschule":338,"id_studien":398,"name":"Business Management - Finance","id_studiengang":9,"Hochschule":"Duale Hochschule Baden-Württemberg","Studienort":"Bad Mergentheim, Friedrichshafen, u.a.","Abschluss":"Master of Arts","Studientyp":"weiterführend","Studienform":"Berufsbegleitend, Berufsintegrierend, Duales Studium"},{"id_hochschule":338,"id_studien":398,"name":"Business Management - General Business Management","id_studiengang":10,"Hochschule":"Duale Hochschule Baden-Württemberg","Studienort":"Bad Mergentheim, Friedrichshafen, u.a.","Abschluss":"Master of Arts","Studientyp":"weiterführend","Studienform":"Berufsbegleitend, Berufsintegrierend, Duales Studium"},{"id_hochschule":338,"id_studien":398,"name":"Business Management - Marketing","id_studiengang":11,"Hochschule":"Duale Hochschule Baden-Württemberg","Studienort":"Bad Mergentheim, Friedrichshafen, u.a.","Abschluss":"Master of Arts","Studientyp":"weiterführend","Studienform":"Berufsbegleitend, Berufsintegrierend, Duales Studium"},{"id_hochschule":338,"id_studien":398,"name":"Business Management - Medien und Marketing","id_studiengang":12,"Hochschule":"Duale Hochschule Baden-Württemberg","Studienort":"Bad Mergentheim, Friedrichshafen, u.a.","Abschluss":"Master of Arts","Studientyp":"weiterführend","Studienform":"Berufsbegleitend, Berufsintegrierend, Duales Studium"},{"id_hochschule":338,"id_studien":398,"name":"Business Management - Personal und Organisation","id_studiengang":13,"Hochschule":"Duale Hochschule Baden-Württemberg","Studienort":"Bad Mergentheim, Friedrichshafen, u.a.","Abschluss":"Master of Arts","Studientyp":"weiterführend","Studienform":"Berufsbegleitend, Berufsintegrierend, Duales Studium"},{"id_hochschule":338,"id_studien":398,"name":"Business Management - Supply Chain Management, Logistik und Produktion","id_studiengang":14,"Hochschule":"Duale Hochschule Baden-Württemberg","Studienort":"Bad Mergentheim, Friedrichshafen, u.a.","Abschluss":"Master of Arts","Studientyp":"weiterführend","Studienform":"Berufsbegleitend, Berufsintegrierend, Duales Studium"},{"id_hochschule":338,"id_studien":398,"name":"BWL - Bank","id_studiengang":15,"Hochschule":"Duale Hochschule Baden-Württemberg","Studienort":"Heidenheim, Karlsruhe, u.a.","Abschluss":"Bachelor of Arts","Studientyp":"grundständig","Studienform":"Duales Studium, Praxisintegrierend, Vollzeitstudium"},{"id_hochschule":338,"id_studien":398,"name":"BWL - Controlling & Consulting","id_studiengang":16,"Hochschule":"Duale Hochschule Baden-Württemberg","Studienort":"Villingen-Schwenningen","Abschluss":"Bachelor of Arts","Studientyp":"grundständig","Studienform":"Duales Studium, Praxisintegrierend, Vollzeitstudium"},{"id_hochschule":338,"id_studien":398,"name":"BWL - Deutsch-Französisches Management","id_studiengang":17,"Hochschule":"Duale Hochschule Baden-Württemberg","Studienort":"Karlsruhe","Abschluss":"Bachelor of Arts","Studientyp":"grundständig","Studienform":"Duales Studium, Praxisintegrierend, Vollzeitstudium"},{"id_hochschule":338,"id_studien":398,"name":"BWL - Dienstleistungsmanagement / -marketing","id_studiengang":18,"Hochschule":"Duale Hochschule Baden-Württemberg","Studienort":"Heidenheim, Heilbronn, u.a.","Abschluss":"Bachelor of Arts","Studientyp":"grundständig","Studienform":"Duales Studium, Praxisintegrierend, Vollzeitstudium"},{"id_hochschule":338,"id_studien":398,"name":"BWL - Finanzdienstleistungen","id_studiengang":19,"Hochschule":"Duale Hochschule Baden-Württemberg","Studienort":"Lörrach, Ravensburg, u.a.","Abschluss":"Bachelor of Arts","Studientyp":"grundständig","Studienform":"Duales Studium, Praxisintegrierend, Vollzeitstudium"},{"id_hochschule":338,"id_studien":398,"name":"BWL - Food Management","id_studiengang":20,"Hochschule":"Duale Hochschule Baden-Württemberg","Studienort":"Heilbronn","Abschluss":"Bachelor of Arts","Studientyp":"grundständig","Studienform":"Duales Studium, Praxisintegrierend, Vollzeitstudium"},{"id_hochschule":338,"id_studien":398,"name":"BWL - Gesundheitsmanagement","id_studiengang":21,"Hochschule":"Duale Hochschule Baden-Württemberg","Studienort":"Lörrach, Mannheim, u.a.","Abschluss":"Bachelor of Arts","Studientyp":"grundständig","Studienform":"Duales Studium, Praxisintegrierend, Vollzeitstudium"},{"id_hochschule":338,"id_studien":398,"name":"BWL - Handel","id_studiengang":22,"Hochschule":"Duale Hochschule Baden-Württemberg","Studienort":"Heidenheim, Heilbronn, u.a.","Abschluss":"Bachelor of Arts","Studientyp":"grundständig","Studienform":"Duales Studium, Praxisintegrierend, Vollzeitstudium"},{"id_hochschule":338,"id_studien":398,"name":"BWL - Handwerk","id_studiengang":23,"Hochschule":"Duale Hochschule Baden-Württemberg","Studienort":"Stuttgart","Abschluss":"Bachelor of Arts","Studientyp":"grundständig","Studienform":"Duales Studium, Praxisintegrierend, Vollzeitstudium"},{"id_hochschule":338,"id_studien":398,"name":"BWL - Immobilienwirtschaft","id_studiengang":24,"Hochschule":"Duale Hochschule Baden-Württemberg","Studienort":"Mannheim , Stuttgart","Abschluss":"Bachelor of Arts","Studientyp":"grundständig","Studienform":"Duales Studium, Praxisintegrierend, Vollzeitstudium"},{"id_hochschule":338,"id_studien":398,"name":"BWL - Industrie","id_studiengang":25,"Hochschule":"Duale Hochschule Baden-Württemberg","Studienort":"Heidenheim, Karlsruhe, u.a.","Abschluss":"Bachelor of Arts","Studientyp":"grundständig","Studienform":"Duales Studium, Praxisintegrierend, Vollzeitstudium"},{"id_hochschule":338,"id_studien":398,"name":"BWL - International Business","id_studiengang":26,"Hochschule":"Duale Hochschule Baden-Württemberg","Studienort":"Bad Mergentheim, Heidenheim, u.a.","Abschluss":"Bachelor of Arts","Studientyp":"grundständig","Studienform":"Duales Studium, Internationaler Studiengang, Praxisintegrierend, Vollzeitstudium"},{"id_hochschule":338,"id_studien":398,"name":"BWL - Medien- und Kommunikationswirtschaft","id_studiengang":27,"Hochschule":"Duale Hochschule Baden-Württemberg","Studienort":"Ravensburg","Abschluss":"Bachelor of Arts","Studientyp":"grundständig","Studienform":"Duales Studium, Praxisintegrierend, Vollzeitstudium"},{"id_hochschule":338,"id_studien":398,"name":"BWL - Messe-, Kongress- und Eventmanagement","id_studiengang":28,"Hochschule":"Duale Hochschule Baden-Württemberg","Studienort":"Mannheim , Ravensburg","Abschluss":"Bachelor of Arts","Studientyp":"grundständig","Studienform":"Duales Studium, Praxisintegrierend, Vollzeitstudium"},{"id_hochschule":338,"id_studien":398,"name":"BWL - Mittelständische Wirtschaft","id_studiengang":29,"Hochschule":"Duale Hochschule Baden-Württemberg","Studienort":"Villingen-Schwenningen","Abschluss":"Bachelor of Arts","Studientyp":"grundständig","Studienform":"Duales Studium, Praxisintegrierend, Vollzeitstudium"},{"id_hochschule":338,"id_studien":398,"name":"BWL - Öffentliche Wirtschaft","id_studiengang":30,"Hochschule":"Duale Hochschule Baden-Württemberg","Studienort":"Mannheim","Abschluss":"Bachelor of Arts","Studientyp":"grundständig","Studienform":"Duales Studium, Praxisintegrierend, Vollzeitstudium"},{"id_hochschule":338,"id_studien":398,"name":"BWL - Personalmanagement","id_studiengang":31,"Hochschule":"Duale Hochschule Baden-Württemberg","Studienort":"Lörrach , Villingen-Schwenningen","Abschluss":"Bachelor of Arts","Studientyp":"grundständig","Studienform":"Duales Studium, Praxisintegrierend, Vollzeitstudium"},{"id_hochschule":338,"id_studien":398,"name":"BWL - Spedition, Transport und Logistik","id_studiengang":32,"Hochschule":"Duale Hochschule Baden-Württemberg","Studienort":"Heidenheim, Lörrach, u.a.","Abschluss":"Bachelor of Arts","Studientyp":"grundständig","Studienform":"Duales Studium, Praxisintegrierend, Vollzeitstudium"},{"id_hochschule":338,"id_studien":398,"name":"BWL - Technical Management","id_studiengang":33,"Hochschule":"Duale Hochschule Baden-Württemberg","Studienort":"Villingen-Schwenningen","Abschluss":"Bachelor of Arts","Studientyp":"grundständig","Studienform":"Duales Studium, Praxisintegrierend, Vollzeitstudium"},{"id_hochschule":338,"id_studien":398,"name":"BWL - Tourismus, Hotellerie und Gastronomie","id_studiengang":34,"Hochschule":"Duale Hochschule Baden-Württemberg","Studienort":"Lörrach , Ravensburg","Abschluss":"Bachelor of Arts","Studientyp":"grundständig","Studienform":"Duales Studium, Praxisintegrierend, Vollzeitstudium"},{"id_hochschule":338,"id_studien":398,"name":"BWL - Versicherung","id_studiengang":35,"Hochschule":"Duale Hochschule Baden-Württemberg","Studienort":"Heidenheim, Karlsruhe, u.a.","Abschluss":"Bachelor of Arts","Studientyp":"grundständig","Studienform":"Duales Studium, Praxisintegrierend, Vollzeitstudium"},{"id_hochschule":338,"id_studien":398,"name":"BWL - Wirtschaftsförderung","id_studiengang":36,"Hochschule":"Duale Hochschule Baden-Württemberg","Studienort":"Mannheim","Abschluss":"Bachelor of Arts","Studientyp":"grundständig","Studienform":"Duales Studium, Praxisintegrierend, Vollzeitstudium"},{"id_hochschule":338,"id_studien":398,"name":"Chemische Technik - Chemie und Bioingenieurwesen","id_studiengang":37,"Hochschule":"Duale Hochschule Baden-Württemberg","Studienort":"Mannheim","Abschluss":"Bachelor of Science","Studientyp":"grundständig","Studienform":"Duales Studium, Praxisintegrierend, Vollzeitstudium"},{"id_hochschule":338,"id_studien":398,"name":"Chemische Technik - Technische und Angewandte Chemie","id_studiengang":38,"Hochschule":"Duale Hochschule Baden-Württemberg","Studienort":"Mannheim","Abschluss":"Bachelor of Science","Studientyp":"grundständig","Studienform":"Duales Studium, Praxisintegrierend, Vollzeitstudium"},{"id_hochschule":338,"id_studien":398,"name":"Elektrotechnik","id_studiengang":39,"Hochschule":"Duale Hochschule Baden-Württemberg","Studienort":"Bad Mergentheim, Friedrichshafen, u.a.","Abschluss":"Master of Engineering","Studientyp":"weiterführend","Studienform":"Berufsbegleitend, Berufsintegrierend, Duales Studium"},{"id_hochschule":338,"id_studien":398,"name":"Elektrotechnik - Automation","id_studiengang":40,"Hochschule":"Duale Hochschule Baden-Württemberg","Studienort":"Friedrichshafen, Horb, u.a.","Abschluss":"Bachelor of Engineering","Studientyp":"grundständig","Studienform":"Duales Studium, Praxisintegrierend, Vollzeitstudium"},{"id_hochschule":338,"id_studien":398,"name":"Elektrotechnik - Elektrische Energietechnik","id_studiengang":41,"Hochschule":"Duale Hochschule Baden-Württemberg","Studienort":"Mannheim","Abschluss":"Bachelor of Engineering","Studientyp":"grundständig","Studienform":"Duales Studium, Praxisintegrierend, Vollzeitstudium"},{"id_hochschule":338,"id_studien":398,"name":"Elektrotechnik - Elektronik","id_studiengang":42,"Hochschule":"Duale Hochschule Baden-Württemberg","Studienort":"Horb, Lörrach, u.a.","Abschluss":"Bachelor of Engineering","Studientyp":"grundständig","Studienform":"Duales Studium, Praxisintegrierend, Vollzeitstudium"},{"id_hochschule":338,"id_studien":398,"name":"Elektrotechnik - Energie- und Umwelttechnik","id_studiengang":43,"Hochschule":"Duale Hochschule Baden-Württemberg","Studienort":"Friedrichshafen , Mannheim","Abschluss":"Bachelor of Engineering","Studientyp":"grundständig","Studienform":"Duales Studium, Praxisintegrierend, Vollzeitstudium"},{"id_hochschule":338,"id_studien":398,"name":"Elektrotechnik - Fahrzeugelektronik","id_studiengang":44,"Hochschule":"Duale Hochschule Baden-Württemberg","Studienort":"Friedrichshafen","Abschluss":"Bachelor of Engineering","Studientyp":"grundständig","Studienform":"Duales Studium, Praxisintegrierend, Vollzeitstudium"},{"id_hochschule":338,"id_studien":398,"name":"Elektrotechnik - Medizintechnik","id_studiengang":45,"Hochschule":"Duale Hochschule Baden-Württemberg","Studienort":"Mannheim","Abschluss":"Bachelor of Engineering","Studientyp":"grundständig","Studienform":"Duales Studium, Praxisintegrierend, Vollzeitstudium"},{"id_hochschule":338,"id_studien":398,"name":"Elektrotechnik - Nachrichtentechnik","id_studiengang":46,"Hochschule":"Duale Hochschule Baden-Württemberg","Studienort":"Friedrichshafen, Karlsruhe, u.a.","Abschluss":"Bachelor of Engineering","Studientyp":"grundständig","Studienform":"Duales Studium, Praxisintegrierend, Vollzeitstudium"},{"id_hochschule":338,"id_studien":398,"name":"Governance Sozialer Arbeit","id_studiengang":47,"Hochschule":"Duale Hochschule Baden-Württemberg","Studienort":"Bad Mergentheim, Friedrichshafen, u.a.","Abschluss":"Master of Arts","Studientyp":"weiterführend","Studienform":"Berufsbegleitend, Berufsintegrierend, Duales Studium"},{"id_hochschule":338,"id_studien":398,"name":"Holztechnik - Holz- und Kunststofftechnik","id_studiengang":48,"Hochschule":"Duale Hochschule Baden-Württemberg","Studienort":"Mosbach","Abschluss":"Bachelor of Engineering","Studientyp":"grundständig","Studienform":"Duales Studium, Praxisintegrierend, Vollzeitstudium"},{"id_hochschule":338,"id_studien":398,"name":"Holztechnik - Studienrichtung Holztechnik","id_studiengang":49,"Hochschule":"Duale Hochschule Baden-Württemberg","Studienort":"Mosbach","Abschluss":"Bachelor of Engineering","Studientyp":"grundständig","Studienform":"Duales Studium, Praxisintegrierend, Vollzeitstudium"},{"id_hochschule":338,"id_studien":398,"name":"Holztechnik - Wirtschaftsingenieurwesen Holztechnik","id_studiengang":50,"Hochschule":"Duale Hochschule Baden-Württemberg","Studienort":"Mosbach","Abschluss":"Bachelor of Engineering","Studientyp":"grundständig","Studienform":"Duales Studium, Praxisintegrierend, Vollzeitstudium"},{"id_hochschule":338,"id_studien":398,"name":"Informatik","id_studiengang":51,"Hochschule":"Duale Hochschule Baden-Württemberg","Studienort":"Bad Mergentheim, Friedrichshafen, u.a.","Abschluss":"Master of Science","Studientyp":"weiterführend","Studienform":"Berufsbegleitend, Berufsintegrierend, Duales Studium"},{"id_hochschule":338,"id_studien":398,"name":"Informatik - Angewandte Informatik","id_studiengang":52,"Hochschule":"Duale Hochschule Baden-Württemberg","Studienort":"Karlsruhe, Lörrach, u.a.","Abschluss":"Bachelor of Science","Studientyp":"grundständig","Studienform":"Duales Studium, Praxisintegrierend, Vollzeitstudium"},{"id_hochschule":338,"id_studien":398,"name":"Informatik - Informationstechnik","id_studiengang":53,"Hochschule":"Duale Hochschule Baden-Württemberg","Studienort":"Friedrichshafen, Heidenheim, u.a.","Abschluss":"Bachelor of Engineering","Studientyp":"grundständig","Studienform":"Duales Studium, Praxisintegrierend, Vollzeitstudium"},{"id_hochschule":338,"id_studien":398,"name":"Informatik - IT Automotive","id_studiengang":54,"Hochschule":"Duale Hochschule Baden-Württemberg","Studienort":"Stuttgart","Abschluss":"Bachelor of Engineering","Studientyp":"grundständig","Studienform":"Duales Studium, Praxisintegrierend, Vollzeitstudium"},{"id_hochschule":338,"id_studien":398,"name":"Informatik - Medizinische Informatik","id_studiengang":55,"Hochschule":"Duale Hochschule Baden-Württemberg","Studienort":"Heidenheim , Karlsruhe","Abschluss":"Bachelor of Science","Studientyp":"grundständig","Studienform":"Duales Studium, Praxisintegrierend, Vollzeitstudium"},{"id_hochschule":338,"id_studien":398,"name":"Informatik - Studienrichtung Informatik","id_studiengang":56,"Hochschule":"Duale Hochschule Baden-Württemberg","Studienort":"Friedrichshafen, Heidenheim, u.a.","Abschluss":"Bachelor of Science","Studientyp":"grundständig","Studienform":"Duales Studium, Praxisintegrierend, Vollzeitstudium"},{"id_hochschule":338,"id_studien":398,"name":"Integrated Engineering","id_studiengang":57,"Hochschule":"Duale Hochschule Baden-Württemberg","Studienort":"Bad Mergentheim, Friedrichshafen, u.a.","Abschluss":"Master of Engineering","Studientyp":"weiterführend","Studienform":"Berufsbegleitend, Berufsintegrierend, Duales Studium"},{"id_hochschule":338,"id_studien":398,"name":"International Business Management (Trinational)","id_studiengang":58,"Hochschule":"Duale Hochschule Baden-Württemberg","Studienort":"Lörrach","Abschluss":"Bachelor of Arts","Studientyp":"grundständig","Studienform":"Duales Studium, Internationaler Studiengang, Praxisintegrierend, Vollzeitstudium"},{"id_hochschule":338,"id_studien":398,"name":"Interprofessionelle Gesundheitsversorgung","id_studiengang":59,"Hochschule":"Duale Hochschule Baden-Württemberg","Studienort":"Heidenheim","Abschluss":"Bachelor of Science","Studientyp":"grundständig","Studienform":"Ausbildungsintegrierend, Duales Studium, Praxisintegrierend, Vollzeitstudium"},{"id_hochschule":338,"id_studien":398,"name":"Luft- und Raumfahrttechnik - Luft- und Raumfahrtelektronik","id_studiengang":60,"Hochschule":"Duale Hochschule Baden-Württemberg","Studienort":"Friedrichshafen","Abschluss":"Bachelor of Engineering","Studientyp":"grundständig","Studienform":"Duales Studium, Praxisintegrierend, Vollzeitstudium"},{"id_hochschule":338,"id_studien":398,"name":"Luft- und Raumfahrttechnik -  Luft- und Raumfahrtsysteme","id_studiengang":61,"Hochschule":"Duale Hochschule Baden-Württemberg","Studienort":"Friedrichshafen","Abschluss":"Bachelor of Engineering","Studientyp":"grundständig","Studienform":"Duales Studium, Praxisintegrierend, Vollzeitstudium"},{"id_hochschule":338,"id_studien":398,"name":"Maschinenbau","id_studiengang":62,"Hochschule":"Duale Hochschule Baden-Württemberg","Studienort":"Bad Mergentheim, Friedrichshafen, u.a.","Abschluss":"Master of Engineering","Studientyp":"weiterführend","Studienform":"Berufsbegleitend, Berufsintegrierend, Duales Studium"},{"id_hochschule":338,"id_studien":398,"name":"Maschinenbau - Allgemeiner Maschinenbau","id_studiengang":63,"Hochschule":"Duale Hochschule Baden-Württemberg","Studienort":"Friedrichshafen, Lörrach, u.a.","Abschluss":"Bachelor of Engineering","Studientyp":"grundständig","Studienform":"Duales Studium, Praxisintegrierend, Vollzeitstudium"},{"id_hochschule":338,"id_studien":398,"name":"Maschinenbau - Fahrzeug-System-Engineering","id_studiengang":64,"Hochschule":"Duale Hochschule Baden-Württemberg","Studienort":"Friedrichshafen , Stuttgart","Abschluss":"Bachelor of Engineering","Studientyp":"grundständig","Studienform":"Duales Studium, Praxisintegrierend, Vollzeitstudium"},{"id_hochschule":338,"id_studien":398,"name":"Maschinenbau - KFZ-Prüftechnik","id_studiengang":65,"Hochschule":"Duale Hochschule Baden-Württemberg","Studienort":"Horb","Abschluss":"Bachelor of Engineering","Studientyp":"grundständig","Studienform":"Duales Studium, Praxisintegrierend, Vollzeitstudium"},{"id_hochschule":338,"id_studien":398,"name":"Maschinenbau - Konstruktion und Entwicklung","id_studiengang":66,"Hochschule":"Duale Hochschule Baden-Württemberg","Studienort":"Friedrichshafen, Heidenheim, u.a.","Abschluss":"Bachelor of Engineering","Studientyp":"grundständig","Studienform":"Duales Studium, Praxisintegrierend, Vollzeitstudium"},{"id_hochschule":338,"id_studien":398,"name":"Maschinenbau - Kunststofftechnik","id_studiengang":67,"Hochschule":"Duale Hochschule Baden-Württemberg","Studienort":"Horb , Mosbach","Abschluss":"Bachelor of Engineering","Studientyp":"grundständig","Studienform":"Duales Studium, Praxisintegrierend, Vollzeitstudium"},{"id_hochschule":338,"id_studien":398,"name":"Maschinenbau - Produktionstechnik","id_studiengang":68,"Hochschule":"Duale Hochschule Baden-Württemberg","Studienort":"Friedrichshafen, Heidenheim, u.a.","Abschluss":"Bachelor of Engineering","Studientyp":"grundständig","Studienform":"Duales Studium, Praxisintegrierend, Vollzeitstudium"},{"id_hochschule":338,"id_studien":398,"name":"Maschinenbau - Verfahrenstechnik","id_studiengang":69,"Hochschule":"Duale Hochschule Baden-Württemberg","Studienort":"Mannheim , Mosbach","Abschluss":"Bachelor of Engineering","Studientyp":"grundständig","Studienform":"Duales Studium, Praxisintegrierend, Vollzeitstudium"},{"id_hochschule":338,"id_studien":398,"name":"Maschinenbau - Versorgungs- und Energiemanagement","id_studiengang":70,"Hochschule":"Duale Hochschule Baden-Württemberg","Studienort":"Horb , Mannheim","Abschluss":"Bachelor of Engineering","Studientyp":"grundständig","Studienform":"Duales Studium, Praxisintegrierend, Vollzeitstudium"},{"id_hochschule":338,"id_studien":398,"name":"Maschinenbau - Virtual Engineering","id_studiengang":71,"Hochschule":"Duale Hochschule Baden-Württemberg","Studienort":"Mosbach","Abschluss":"Bachelor of Engineering","Studientyp":"grundständig","Studienform":"Duales Studium, Praxisintegrierend, Vollzeitstudium"},{"id_hochschule":338,"id_studien":398,"name":"Mechatronik - Allgemeine Mechatronik","id_studiengang":72,"Hochschule":"Duale Hochschule Baden-Württemberg","Studienort":"Horb, Karlsruhe, u.a.","Abschluss":"Bachelor of Engineering","Studientyp":"grundständig","Studienform":"Duales Studium, Praxisintegrierend, Vollzeitstudium"},{"id_hochschule":338,"id_studien":398,"name":"Mechatronik - Energiewirtschaft","id_studiengang":73,"Hochschule":"Duale Hochschule Baden-Württemberg","Studienort":"Mannheim","Abschluss":"Bachelor of Engineering","Studientyp":"grundständig","Studienform":"Duales Studium, Praxisintegrierend, Vollzeitstudium"},{"id_hochschule":338,"id_studien":398,"name":"Mechatronik - Fahrzeugsystemtechnik und Elektromobilität","id_studiengang":74,"Hochschule":"Duale Hochschule Baden-Württemberg","Studienort":"Horb, Mannheim, u.a.","Abschluss":"Bachelor of Engineering","Studientyp":"grundständig","Studienform":"Duales Studium, Praxisintegrierend, Vollzeitstudium"},{"id_hochschule":338,"id_studien":398,"name":"Mechatronik - Projekt-Engineering","id_studiengang":75,"Hochschule":"Duale Hochschule Baden-Württemberg","Studienort":"Mannheim","Abschluss":"Bachelor of Engineering","Studientyp":"grundständig","Studienform":"Duales Studium, Praxisintegrierend, Vollzeitstudium"},{"id_hochschule":338,"id_studien":398,"name":"Mechatronik - Serviceingenieurwesen","id_studiengang":76,"Hochschule":"Duale Hochschule Baden-Württemberg","Studienort":"Mannheim","Abschluss":"Bachelor of Engineering","Studientyp":"grundständig","Studienform":"Duales Studium, Praxisintegrierend, Vollzeitstudium"},{"id_hochschule":338,"id_studien":398,"name":"Mechatronik (Trinational)","id_studiengang":77,"Hochschule":"Duale Hochschule Baden-Württemberg","Studienort":"Lörrach","Abschluss":"Bachelor of Engineering","Studientyp":"grundständig","Studienform":"Duales Studium, Internationaler Studiengang, Praxisintegrierend, Vollzeitstudium"},{"id_hochschule":338,"id_studien":398,"name":"Medien - Digitale Medien ","id_studiengang":78,"Hochschule":"Duale Hochschule Baden-Württemberg","Studienort":"Mannheim","Abschluss":"Bachelor of Arts","Studientyp":"grundständig","Studienform":"Duales Studium, Praxisintegrierend, Vollzeitstudium"},{"id_hochschule":338,"id_studien":398,"name":"Medien - Mediendesign","id_studiengang":79,"Hochschule":"Duale Hochschule Baden-Württemberg","Studienort":"Ravensburg","Abschluss":"Bachelor of Arts","Studientyp":"grundständig","Studienform":"Duales Studium, Praxisintegrierend, Vollzeitstudium"},{"id_hochschule":338,"id_studien":398,"name":"Medien - Onlinemedien","id_studiengang":80,"Hochschule":"Duale Hochschule Baden-Württemberg","Studienort":"Mosbach","Abschluss":"Bachelor of Arts","Studientyp":"grundständig","Studienform":"Duales Studium, Praxisintegrierend, Vollzeitstudium"},{"id_hochschule":338,"id_studien":398,"name":"Medizintechnische Wissenschaften","id_studiengang":81,"Hochschule":"Duale Hochschule Baden-Württemberg","Studienort":"Heidenheim","Abschluss":"Bachelor of Science","Studientyp":"grundständig","Studienform":"Duales Studium, Praxisintegrierend, Vollzeitstudium"},{"id_hochschule":338,"id_studien":398,"name":"Papiertechnik - Papiererzeugung","id_studiengang":82,"Hochschule":"Duale Hochschule Baden-Württemberg","Studienort":"Karlsruhe","Abschluss":"Bachelor of Engineering","Studientyp":"grundständig","Studienform":"Duales Studium, Praxisintegrierend, Vollzeitstudium"},{"id_hochschule":338,"id_studien":398,"name":"Papiertechnik - Verpackungsherstellung","id_studiengang":83,"Hochschule":"Duale Hochschule Baden-Württemberg","Studienort":"Karlsruhe","Abschluss":"Bachelor of Engineering","Studientyp":"grundständig","Studienform":"Duales Studium, Praxisintegrierend, Vollzeitstudium"},{"id_hochschule":338,"id_studien":398,"name":"Physician Assistant (Arztassistent/ -in)","id_studiengang":84,"Hochschule":"Duale Hochschule Baden-Württemberg","Studienort":"Karlsruhe","Abschluss":"Bachelor of Science","Studientyp":"grundständig","Studienform":"Duales Studium, Praxisintegrierend, Vollzeitstudium"},{"id_hochschule":338,"id_studien":398,"name":"Physiotherapie","id_studiengang":85,"Hochschule":"Duale Hochschule Baden-Württemberg","Studienort":"Lörrach","Abschluss":"Bachelor of Science","Studientyp":"grundständig","Studienform":"Ausbildungsintegrierend, Duales Studium, Praxisintegrierend, Vollzeitstudium"},{"id_hochschule":338,"id_studien":398,"name":"Rechnungswesen Steuern Wirtschaftsrecht - Accounting & Controlling","id_studiengang":86,"Hochschule":"Duale Hochschule Baden-Württemberg","Studienort":"Mannheim , Stuttgart","Abschluss":"Bachelor of Arts","Studientyp":"grundständig","Studienform":"Duales Studium, Praxisintegrierend, Vollzeitstudium"},{"id_hochschule":338,"id_studien":398,"name":"Rechnungswesen Steuern Wirtschaftsrecht - Betriebswirtschaftliche Steuerlehre, Unternehmensrechnung und Finanzen","id_studiengang":87,"Hochschule":"Duale Hochschule Baden-Württemberg","Studienort":"Mosbach","Abschluss":"Bachelor of Arts","Studientyp":"grundständig","Studienform":"Duales Studium, Praxisintegrierend, Vollzeitstudium"},{"id_hochschule":338,"id_studien":398,"name":"Rechnungswesen Steuern Wirtschaftsrecht - Steuern und Prüfungswesen","id_studiengang":88,"Hochschule":"Duale Hochschule Baden-Württemberg","Studienort":"Karlsruhe, Mannheim, u.a.","Abschluss":"Bachelor of Arts","Studientyp":"grundständig","Studienform":"Duales Studium, Praxisintegrierend, Vollzeitstudium"},{"id_hochschule":338,"id_studien":398,"name":"Rechnungswesen Steuern Wirtschaftsrecht - Wirtschaftsprüfung","id_studiengang":89,"Hochschule":"Duale Hochschule Baden-Württemberg","Studienort":"Stuttgart , Villingen-Schwenningen","Abschluss":"Bachelor of Arts","Studientyp":"grundständig","Studienform":"Duales Studium, Praxisintegrierend, Vollzeitstudium"},{"id_hochschule":338,"id_studien":398,"name":"Sicherheitswesen - Arbeitssicherheit","id_studiengang":90,"Hochschule":"Duale Hochschule Baden-Württemberg","Studienort":"Karlsruhe","Abschluss":"Bachelor of Science","Studientyp":"grundständig","Studienform":"Duales Studium, Praxisintegrierend, Vollzeitstudium"},{"id_hochschule":338,"id_studien":398,"name":"Sicherheitswesen - Strahlenschutz","id_studiengang":91,"Hochschule":"Duale Hochschule Baden-Württemberg","Studienort":"Karlsruhe","Abschluss":"Bachelor of Science","Studientyp":"grundständig","Studienform":"Duales Studium, Praxisintegrierend, Vollzeitstudium"},{"id_hochschule":338,"id_studien":398,"name":"Sicherheitswesen - Umwelttechnik","id_studiengang":92,"Hochschule":"Duale Hochschule Baden-Württemberg","Studienort":"Karlsruhe","Abschluss":"Bachelor of Science","Studientyp":"grundständig","Studienform":"Duales Studium, Praxisintegrierend, Vollzeitstudium"},{"id_hochschule":338,"id_studien":398,"name":"Soziale Arbeit - Arbeit, Integration und soziale Sicherung","id_studiengang":93,"Hochschule":"Duale Hochschule Baden-Württemberg","Studienort":"Stuttgart","Abschluss":"Bachelor of Arts","Studientyp":"grundständig","Studienform":"Duales Studium, Praxisintegrierend, Vollzeitstudium"},{"id_hochschule":338,"id_studien":398,"name":"Soziale Arbeit - Bildung und Beruf","id_studiengang":94,"Hochschule":"Duale Hochschule Baden-Württemberg","Studienort":"Villingen-Schwenningen","Abschluss":"Bachelor of Arts","Studientyp":"grundständig","Studienform":"Duales Studium, Praxisintegrierend, Vollzeitstudium"},{"id_hochschule":338,"id_studien":398,"name":"Soziale Arbeit - Case Management im Sozial- und Gesundheitswesen","id_studiengang":95,"Hochschule":"Duale Hochschule Baden-Württemberg","Studienort":"Heidenheim","Abschluss":"Bachelor of Arts","Studientyp":"grundständig","Studienform":"Duales Studium, Praxisintegrierend, Vollzeitstudium"},{"id_hochschule":338,"id_studien":398,"name":"Soziale Arbeit - Erziehungshilfen /  Kinder- und Jugendhilfe","id_studiengang":96,"Hochschule":"Duale Hochschule Baden-Württemberg","Studienort":"Heidenheim , Stuttgart","Abschluss":"Bachelor of Arts","Studientyp":"grundständig","Studienform":"Duales Studium, Praxisintegrierend, Vollzeitstudium"},{"id_hochschule":338,"id_studien":398,"name":"Soziale Arbeit in der Migrationsgesellschaft","id_studiengang":97,"Hochschule":"Duale Hochschule Baden-Württemberg","Studienort":"Bad Mergentheim, Friedrichshafen, u.a.","Abschluss":"Master of Arts","Studientyp":"weiterführend","Studienform":"Berufsbegleitend, Berufsintegrierend, Duales Studium"},{"id_hochschule":338,"id_studien":398,"name":"Soziale Arbeit - Jugend-, Familien- und Sozialhilfe","id_studiengang":98,"Hochschule":"Duale Hochschule Baden-Württemberg","Studienort":"Heidenheim, Stuttgart, u.a.","Abschluss":"Bachelor of Arts","Studientyp":"grundständig","Studienform":"Duales Studium, Praxisintegrierend, Vollzeitstudium"},{"id_hochschule":338,"id_studien":398,"name":"Soziale Arbeit - Kinder- und Jugendarbeit","id_studiengang":99,"Hochschule":"Duale Hochschule Baden-Württemberg","Studienort":"Stuttgart","Abschluss":"Bachelor of Arts","Studientyp":"grundständig","Studienform":"Duales Studium, Praxisintegrierend, Vollzeitstudium"}]