[{"id_hochschule":242,"id_studien":452,"name":"Design- und Innovationsmanagement","id_studiengang":452,"Hochschule":"Vitruvius Hochschule Leipzig","Studienort":"Leipzig","Abschluss":"Bachelor of Arts","Studientyp":"grundständig","Studienform":"Vollzeitstudium"},{"id_hochschule":242,"id_studien":452,"name":"Gamedesign","id_studiengang":1,"Hochschule":"Vitruvius Hochschule Leipzig","Studienort":"Leipzig , Schwerin","Abschluss":"Bachelor of Arts","Studientyp":"grundständig","Studienform":"Vollzeitstudium"},{"id_hochschule":242,"id_studien":452,"name":"Kommunikationsdesign","id_studiengang":2,"Hochschule":"Vitruvius Hochschule Leipzig","Studienort":"Leipzig , Schwerin","Abschluss":"Bachelor of Arts","Studientyp":"grundständig","Studienform":"Vollzeitstudium"},{"id_hochschule":242,"id_studien":452,"name":"Modedesign","id_studiengang":3,"Hochschule":"Vitruvius Hochschule Leipzig","Studienort":"Leipzig , Schwerin","Abschluss":"Bachelor of Arts","Studientyp":"grundständig","Studienform":"Vollzeitstudium"},{"id_hochschule":242,"id_studien":452,"name":"Software Engineering & Information Security","id_studiengang":4,"Hochschule":"Vitruvius Hochschule Leipzig","Studienort":"Leipzig","Abschluss":"Bachelor of Science","Studientyp":"grundständig","Studienform":"Teilzeitstudium, Vollzeitstudium"}]