[{"id_hochschule":110,"id_studien":66,"name":"Angewandte Linguistik  Erwerb, Verarbeitung und Verwendung von Sprache","id_studiengang":66,"Hochschule":"Universität Erfurt","Studienort":"Erfurt","Abschluss":"Master","Studientyp":"weiterführend","Studienform":"Teilzeitstudium, Vollzeitstudium"},{"id_hochschule":110,"id_studien":66,"name":"Anglistik/ Amerikanistik","id_studiengang":1,"Hochschule":"Universität Erfurt","Studienort":"Erfurt","Abschluss":"Bachelor (2-Fach-Bachelor)","Studientyp":"grundständig","Studienform":"Teilzeitstudium, Vollzeitstudium"},{"id_hochschule":110,"id_studien":66,"name":"Erziehungswissenschaft","id_studiengang":2,"Hochschule":"Universität Erfurt","Studienort":"Erfurt","Abschluss":"Bachelor (2-Fach-Bachelor)","Studientyp":"grundständig","Studienform":"Teilzeitstudium, Vollzeitstudium"},{"id_hochschule":110,"id_studien":66,"name":"Erziehungswissenschaft - Innovation und Management im Bildungswesen","id_studiengang":3,"Hochschule":"Universität Erfurt","Studienort":"Erfurt","Abschluss":"Master","Studientyp":"weiterführend","Studienform":"Teilzeitstudium, Vollzeitstudium"},{"id_hochschule":110,"id_studien":66,"name":"Förderpädagogik","id_studiengang":4,"Hochschule":"Universität Erfurt","Studienort":"Erfurt","Abschluss":"Bachelor (2-Fach-Bachelor)","Studientyp":"grundständig","Studienform":"Teilzeitstudium, Vollzeitstudium"},{"id_hochschule":110,"id_studien":66,"name":"Germanistik","id_studiengang":5,"Hochschule":"Universität Erfurt","Studienort":"Erfurt","Abschluss":"Bachelor (2-Fach-Bachelor)","Studientyp":"grundständig","Studienform":"Teilzeitstudium, Vollzeitstudium"},{"id_hochschule":110,"id_studien":66,"name":"Geschichte und Soziologie/ Anthropologie des Vorderen Orients in globaler Perspektive","id_studiengang":6,"Hochschule":"Universität Erfurt","Studienort":"Erfurt","Abschluss":"Master","Studientyp":"weiterführend","Studienform":"Internationaler Studiengang, Teilzeitstudium, Vollzeitstudium"},{"id_hochschule":110,"id_studien":66,"name":"Geschichtswissenschaft","id_studiengang":7,"Hochschule":"Universität Erfurt","Studienort":"Erfurt","Abschluss":"Bachelor (2-Fach-Bachelor)","Studientyp":"grundständig","Studienform":"Teilzeitstudium, Vollzeitstudium"},{"id_hochschule":110,"id_studien":66,"name":"Geschichtswissenschaft","id_studiengang":8,"Hochschule":"Universität Erfurt","Studienort":"Erfurt","Abschluss":"Master","Studientyp":"weiterführend","Studienform":"Teilzeitstudium, Vollzeitstudium"},{"id_hochschule":110,"id_studien":66,"name":"Gesundheitskommunikation","id_studiengang":9,"Hochschule":"Universität Erfurt","Studienort":"Erfurt","Abschluss":"Master","Studientyp":"weiterführend","Studienform":"Teilzeitstudium, Vollzeitstudium"},{"id_hochschule":110,"id_studien":66,"name":"Internationale Beziehungen","id_studiengang":10,"Hochschule":"Universität Erfurt","Studienort":"Erfurt","Abschluss":"Bachelor (2-Fach-Bachelor)","Studientyp":"grundständig","Studienform":"Teilzeitstudium, Vollzeitstudium"},{"id_hochschule":110,"id_studien":66,"name":"Kinder- und Jugendmedien","id_studiengang":11,"Hochschule":"Universität Erfurt","Studienort":"Erfurt","Abschluss":"Master","Studientyp":"weiterführend","Studienform":"Teilzeitstudium, Vollzeitstudium"},{"id_hochschule":110,"id_studien":66,"name":"Kommunikationsforschung: Politik und Gesellschaft","id_studiengang":12,"Hochschule":"Universität Erfurt","Studienort":"Erfurt","Abschluss":"Master","Studientyp":"weiterführend","Studienform":"Teilzeitstudium, Vollzeitstudium"},{"id_hochschule":110,"id_studien":66,"name":"Kommunikationswissenschaft","id_studiengang":13,"Hochschule":"Universität Erfurt","Studienort":"Erfurt","Abschluss":"Bachelor (2-Fach-Bachelor)","Studientyp":"grundständig","Studienform":"Teilzeitstudium, Vollzeitstudium"},{"id_hochschule":110,"id_studien":66,"name":"Kunst","id_studiengang":14,"Hochschule":"Universität Erfurt","Studienort":"Erfurt","Abschluss":"Bachelor (2-Fach-Bachelor)","Studientyp":"grundständig","Studienform":"Teilzeitstudium, Vollzeitstudium"},{"id_hochschule":110,"id_studien":66,"name":"Lehramt Berufsbildende Schulen","id_studiengang":15,"Hochschule":"Universität Erfurt","Studienort":"Erfurt","Abschluss":"Master of Education Berufsbildende Schulen","Studientyp":"weiterführend","Studienform":"Teilzeitstudium, Vollzeitstudium"},{"id_hochschule":110,"id_studien":66,"name":"Lehramt Förderpädagogik","id_studiengang":16,"Hochschule":"Universität Erfurt","Studienort":"Erfurt","Abschluss":"Master of Education Förderpäda­gogik","Studientyp":"weiterführend","Studienform":"Teilzeitstudium, Vollzeitstudium"},{"id_hochschule":110,"id_studien":66,"name":"Lehramt Grundschule","id_studiengang":17,"Hochschule":"Universität Erfurt","Studienort":"Erfurt","Abschluss":"Master of Education Grundschule","Studientyp":"weiterführend","Studienform":"Teilzeitstudium, Vollzeitstudium"},{"id_hochschule":110,"id_studien":66,"name":"Lehramt Regelschule","id_studiengang":18,"Hochschule":"Universität Erfurt","Studienort":"Erfurt","Abschluss":"Master of Education Regelschule","Studientyp":"weiterführend","Studienform":"Teilzeitstudium, Vollzeitstudium"},{"id_hochschule":110,"id_studien":66,"name":"Lehr-, Lern- und Trainingspsychologie","id_studiengang":19,"Hochschule":"Universität Erfurt","Studienort":"Erfurt","Abschluss":"Bachelor (2-Fach-Bachelor)","Studientyp":"grundständig","Studienform":"Teilzeitstudium, Vollzeitstudium"},{"id_hochschule":110,"id_studien":66,"name":"Literaturwissenschaft","id_studiengang":20,"Hochschule":"Universität Erfurt","Studienort":"Erfurt","Abschluss":"Bachelor (2-Fach-Bachelor)","Studientyp":"grundständig","Studienform":"Teilzeitstudium, Vollzeitstudium"},{"id_hochschule":110,"id_studien":66,"name":"Literaturwissenschaft:Texte.Zeichen.Medien","id_studiengang":21,"Hochschule":"Universität Erfurt","Studienort":"Erfurt","Abschluss":"Master","Studientyp":"weiterführend","Studienform":"Teilzeitstudium, Vollzeitstudium"},{"id_hochschule":110,"id_studien":66,"name":"Management","id_studiengang":22,"Hochschule":"Universität Erfurt","Studienort":"Erfurt","Abschluss":"Bachelor (2-Fach-Bachelor)","Studientyp":"grundständig","Studienform":"Teilzeitstudium, Vollzeitstudium"},{"id_hochschule":110,"id_studien":66,"name":"Mathematik","id_studiengang":23,"Hochschule":"Universität Erfurt","Studienort":"Erfurt","Abschluss":"Bachelor (2-Fach-Bachelor)","Studientyp":"grundständig","Studienform":"Teilzeitstudium, Vollzeitstudium"},{"id_hochschule":110,"id_studien":66,"name":"Musikerziehung","id_studiengang":24,"Hochschule":"Universität Erfurt","Studienort":"Erfurt","Abschluss":"Bachelor (2-Fach-Bachelor)","Studientyp":"grundständig","Studienform":"Teilzeitstudium, Vollzeitstudium"},{"id_hochschule":110,"id_studien":66,"name":"Musikvermittlung","id_studiengang":25,"Hochschule":"Universität Erfurt","Studienort":"Erfurt","Abschluss":"Bachelor (2-Fach-Bachelor)","Studientyp":"grundständig","Studienform":"Teilzeitstudium, Vollzeitstudium"},{"id_hochschule":110,"id_studien":66,"name":"Philosophie","id_studiengang":26,"Hochschule":"Universität Erfurt","Studienort":"Erfurt","Abschluss":"Bachelor (2-Fach-Bachelor)","Studientyp":"grundständig","Studienform":"Teilzeitstudium, Vollzeitstudium"},{"id_hochschule":110,"id_studien":66,"name":"Philosophie (Sprache-Wissen-Handlung)","id_studiengang":27,"Hochschule":"Universität Erfurt","Studienort":"Erfurt","Abschluss":"Master","Studientyp":"weiterführend","Studienform":"Teilzeitstudium, Vollzeitstudium"},{"id_hochschule":110,"id_studien":66,"name":"Primare und elementare Bildung","id_studiengang":28,"Hochschule":"Universität Erfurt","Studienort":"Erfurt","Abschluss":"Bachelor (2-Fach-Bachelor)","Studientyp":"grundständig","Studienform":"Teilzeitstudium, Vollzeitstudium"},{"id_hochschule":110,"id_studien":66,"name":"Psychologie mit dem Schwerpunkt Lehren, Lernen und Komptenzentwicklung","id_studiengang":29,"Hochschule":"Universität Erfurt","Studienort":"Erfurt","Abschluss":"Master","Studientyp":"weiterführend","Studienform":"Teilzeitstudium, Vollzeitstudium"},{"id_hochschule":110,"id_studien":66,"name":"Public Policy (Politikwissenschaft)","id_studiengang":30,"Hochschule":"Universität Erfurt","Studienort":"Erfurt","Abschluss":"Master","Studientyp":"weiterführend","Studienform":"Vollzeitstudium"},{"id_hochschule":110,"id_studien":66,"name":"Religion, katholische","id_studiengang":31,"Hochschule":"Universität Erfurt","Studienort":"Erfurt","Abschluss":"Bachelor (2-Fach-Bachelor)","Studientyp":"grundständig","Studienform":"Teilzeitstudium, Vollzeitstudium"},{"id_hochschule":110,"id_studien":66,"name":"Religionslehre, evangelische","id_studiengang":32,"Hochschule":"Universität Erfurt","Studienort":"Erfurt","Abschluss":"Bachelor (2-Fach-Bachelor)","Studientyp":"grundständig","Studienform":"Teilzeitstudium, Vollzeitstudium"},{"id_hochschule":110,"id_studien":66,"name":"Religionswissenschaft","id_studiengang":33,"Hochschule":"Universität Erfurt","Studienort":"Erfurt","Abschluss":"Bachelor (2-Fach-Bachelor)","Studientyp":"grundständig","Studienform":"Teilzeitstudium, Vollzeitstudium"},{"id_hochschule":110,"id_studien":66,"name":"Religionswissenschaft","id_studiengang":34,"Hochschule":"Universität Erfurt","Studienort":"Erfurt","Abschluss":"Master","Studientyp":"weiterführend","Studienform":"Teilzeitstudium, Vollzeitstudium"},{"id_hochschule":110,"id_studien":66,"name":"Romanistik","id_studiengang":35,"Hochschule":"Universität Erfurt","Studienort":"Erfurt","Abschluss":"Bachelor (2-Fach-Bachelor)","Studientyp":"grundständig","Studienform":"Teilzeitstudium, Vollzeitstudium"},{"id_hochschule":110,"id_studien":66,"name":"Sammlungsbezogene Wissens- und Kulturgeschichte","id_studiengang":36,"Hochschule":"Universität Erfurt","Studienort":"Erfurt","Abschluss":"Master","Studientyp":"weiterführend","Studienform":"Teilzeitstudium, Vollzeitstudium"},{"id_hochschule":110,"id_studien":66,"name":"Slawistik","id_studiengang":37,"Hochschule":"Universität Erfurt","Studienort":"Erfurt","Abschluss":"Bachelor (2-Fach-Bachelor)","Studientyp":"grundständig","Studienform":"Teilzeitstudium, Vollzeitstudium"},{"id_hochschule":110,"id_studien":66,"name":"Sonder- und Integrationspädagogik","id_studiengang":38,"Hochschule":"Universität Erfurt","Studienort":"Erfurt","Abschluss":"Master","Studientyp":"weiterführend","Studienform":"Teilzeitstudium, Vollzeitstudium"},{"id_hochschule":110,"id_studien":66,"name":"Sport- und Bewegungspädagogik","id_studiengang":39,"Hochschule":"Universität Erfurt","Studienort":"Erfurt","Abschluss":"Bachelor (2-Fach-Bachelor)","Studientyp":"grundständig","Studienform":"Teilzeitstudium, Vollzeitstudium"},{"id_hochschule":110,"id_studien":66,"name":"Staatswissenschaften","id_studiengang":40,"Hochschule":"Universität Erfurt","Studienort":"Erfurt","Abschluss":"Master","Studientyp":"weiterführend","Studienform":"Teilzeitstudium, Vollzeitstudium"},{"id_hochschule":110,"id_studien":66,"name":"Staatswissenschaften - Rechtswissenschaft","id_studiengang":41,"Hochschule":"Universität Erfurt","Studienort":"Erfurt","Abschluss":"Bachelor (2-Fach-Bachelor)","Studientyp":"grundständig","Studienform":"Teilzeitstudium, Vollzeitstudium"},{"id_hochschule":110,"id_studien":66,"name":"Staatswissenschaften - Sozialwissenschaften (Politik/ Politikwissenschaft und Soziologie)","id_studiengang":42,"Hochschule":"Universität Erfurt","Studienort":"Erfurt","Abschluss":"Bachelor (2-Fach-Bachelor)","Studientyp":"grundständig","Studienform":"Teilzeitstudium, Vollzeitstudium"},{"id_hochschule":110,"id_studien":66,"name":"Staatswissenschaften-Wirtschaftswissenschaft","id_studiengang":43,"Hochschule":"Universität Erfurt","Studienort":"Erfurt","Abschluss":"Bachelor (2-Fach-Bachelor)","Studientyp":"grundständig","Studienform":"Teilzeitstudium, Vollzeitstudium"},{"id_hochschule":110,"id_studien":66,"name":"Technik","id_studiengang":44,"Hochschule":"Universität Erfurt,Fachhochschule Erfurt","Studienort":"Erfurt","Abschluss":"Bachelor (2-Fach-Bachelor)","Studientyp":"grundständig","Studienform":"Teilzeitstudium, Vollzeitstudium"},{"id_hochschule":110,"id_studien":66,"name":"Theologie, katholische","id_studiengang":45,"Hochschule":"Universität Erfurt","Studienort":"Erfurt","Abschluss":"Lizentiaten­prüfung","Studientyp":"weiterführend","Studienform":"Teilzeitstudium, Vollzeitstudium"},{"id_hochschule":110,"id_studien":66,"name":"Theologie, katholische","id_studiengang":46,"Hochschule":"Universität Erfurt","Studienort":"Erfurt","Abschluss":"Magister","Studientyp":"grundständig","Studienform":"Teilzeitstudium, Vollzeitstudium"},{"id_hochschule":110,"id_studien":66,"name":"Theologie und Wirtschaft","id_studiengang":47,"Hochschule":"Universität Erfurt","Studienort":"Erfurt","Abschluss":"Master","Studientyp":"weiterführend","Studienform":"Teilzeitstudium, Vollzeitstudium"}]